ChangeLog
LICENSE
MANIFEST.in
README.md
cdmcfparserversion.py
setup.py
cdmcfparser.egg-info/PKG-INFO
cdmcfparser.egg-info/SOURCES.txt
cdmcfparser.egg-info/dependency_links.txt
cdmcfparser.egg-info/top_level.txt
src/cflowcomments.cpp
src/cflowcomments.hpp
src/cflowdocs.hpp
src/cflowfragments.cpp
src/cflowfragments.hpp
src/cflowfragmenttypes.hpp
src/cflowmodule.cpp
src/cflowmodule.hpp
src/cflowparser.cpp
src/cflowparser.hpp
src/cflowutils.cpp
src/cflowutils.hpp
src/cflowversion.hpp
tests/bang.ok
tests/bang.py
tests/basicfor.ok
tests/basicfor.py
tests/basicif.ok
tests/basicif.py
tests/basicwhile.ok
tests/basicwhile.py
tests/class_defs.ok
tests/class_defs.py
tests/cml1.ok
tests/cml1.py
tests/cml2.ok
tests/cml2.py
tests/cml3.ok
tests/cml3.py
tests/cml4.ok
tests/cml4.py
tests/cml5.ok
tests/cml5.py
tests/cml6.ok
tests/cml6.py
tests/cml7.ok
tests/cml7.py
tests/coding1.ok
tests/coding1.py
tests/coding2.ok
tests/coding2.py
tests/coding3.ok
tests/coding3.py
tests/commentsonly.ok
tests/commentsonly.py
tests/decorators.ok
tests/decorators.py
tests/docstring.ok
tests/docstring.py
tests/docstring1.ok
tests/docstring1.py
tests/docstring2.ok
tests/docstring2.py
tests/docstring3.ok
tests/docstring3.py
tests/docstring4.ok
tests/docstring4.py
tests/docstring5.ok
tests/docstring5.py
tests/docstring6.ok
tests/docstring6.py
tests/docstring7.ok
tests/docstring7.py
tests/docstringcomments.ok
tests/docstringcomments.py
tests/empty.ok
tests/empty.py
tests/empty_brackets.ok
tests/empty_brackets.py
tests/errors.ok
tests/errors.py
tests/func_annotations.ok
tests/func_annotations.py
tests/func_comments.ok
tests/func_comments.py
tests/func_defs.ok
tests/func_defs.py
tests/import.ok
tests/import.py
tests/noendofline.ok
tests/noendofline.py
tests/notbang.ok
tests/notbang.py
tests/one_comment.ok
tests/one_comment.py
tests/returnmultiline.ok
tests/returnmultiline.py
tests/stringliteral1.ok
tests/stringliteral1.py
tests/stringliteral2.ok
tests/stringliteral2.py
tests/stringliteral3.ok
tests/stringliteral3.py
tests/stringliteral4.ok
tests/stringliteral4.py
tests/stringliteral5.ok
tests/stringliteral5.py
tests/trailingcomments.ok
