Metadata-Version: 1.2
Name: cdmcfparser
Version: 2.4.1
Summary: Python language control flow parser. Written as a part of the Codimension project, this parser aims at pulling all the necessery data to build a control flow diagram.
Home-page: https://github.com/SergeySatskiy/cdm-flowparser
Author: Sergey Satskiy
Author-email: sergey.satskiy@gmail.com
License: GPLv3
Platform: any
Classifier: Development Status :: 5 - Production/Stable
Classifier: Intended Audience :: Developers
Classifier: License :: OSI Approved :: GNU General Public License (GPL)
Classifier: Operating System :: POSIX :: Linux
Classifier: Programming Language :: C++
Classifier: Programming Language :: Python :: 3
Classifier: Topic :: Software Development :: Libraries :: Python Modules
Requires-Python: >=3.5, <3.10
